py_magister/__init__.py
py_magister/access_manager.py
py_magister/apps.py
py_magister/models.py
py_magister/core/__init__.py
py_magister/core/exceptions.py
py_magister/core/models.py
py_magister/core/schema_access.py
py_magister/core/utils.py
py_magister-0.0.21.dist-info/licenses/LICENSE
py_magister-0.0.21.dist-info/METADATA
py_magister-0.0.21.dist-info/WHEEL
py_magister-0.0.21.dist-info/top_level.txt
py_magister-0.0.21.dist-info/RECORD
