Metadata-Version: 2.4
Name: py_magister
Version: 0.0.21
Summary: Django application designed to provide comprehensive access control
Author-email: Adel ESMAIRI <esmairi.github@gmail.com>
Project-URL: Homepage, https://github.com/esmairi/py-magister
Project-URL: Repository, https://github.com/esmairi/py-magister
Keywords: py_magister,magister,authorization,access,control,permission,django
Classifier: Development Status :: 4 - Beta
Classifier: Intended Audience :: Developers
Classifier: Topic :: Software Development :: Libraries
Classifier: License :: OSI Approved :: MIT License
Classifier: Programming Language :: Python :: 3.12
Classifier: Operating System :: OS Independent
Requires-Python: >=3.12
License-File: LICENSE
Requires-Dist: django
Provides-Extra: dev
Requires-Dist: build; extra == "dev"
Requires-Dist: twine; extra == "dev"
Requires-Dist: pytest; extra == "dev"
Requires-Dist: pytest-django; extra == "dev"
Requires-Dist: pre-commit; extra == "dev"
Requires-Dist: black; extra == "dev"
Requires-Dist: flake8; extra == "dev"
Requires-Dist: mypy; extra == "dev"
Requires-Dist: django-stubs; extra == "dev"
Dynamic: license-file
